Metadata-Version: 1.1
Name: HelloThere
Version: 0.0.1
Summary: A Package That Has One Function.
Home-page: UNKNOWN
Author: Danny Wang
Author-email: thepeeps91@gmail.com
License: MIT
Keywords: calculator
Platform: UNKNOWN
Classifier: Development Status :: 5 - Production/Stable
Classifier: Intended Audience :: Education
Classifier: Operating System :: Microsoft :: Windows :: Windows 10
Classifier: License :: OSI Approved :: MIT License
Classifier: Programming Language :: Python :: 3
